[
  {
    "id": "127074",
    "name": "Dining table, extendable 4 to 6 seater",
    "description": "Posting on behalf of donor. \n\nItem: Extendable 4 to 6 seater table \n\nCondition: Sturdy and good working condition. 4 seater can to a 6 seater. \n\nDimensions: x 85cm (W) x 75cm (H) x 140-220 cm (L) (4 seater to 6 seater). \n\nRequests by donor: \n(1) Client to be staying in southwest/south area, not too far from Holland area\n(2) To share a brief description of client circumstance so that donor understand whom she is helping. \n(3) To share sincere words of thanks by the client Thank you!",
    "location": "Ardmore, Bukit Timah, Holland Road, Tanglin",
    "validTill": "30 Oct 2023",
    "ageInYears": 4,
    "dimensions": null,
    "deliveryCostsCoveredByDonor": true
  },
  {
    "id": "127073",
    "name": "King size bed",
    "description": "Beautiful king size mattress that comes with two sets of bedsheets, pillows, blankets, bolster and mattress protector.",
    "location": null,
    "validTill": "28 Oct 2023",
    "ageInYears": 4,
    "dimensions": "175cm (W) x 200cm (L)",
    "deliveryCostsCoveredByDonor": true
  },
  {
    "id": "127072",
    "name": "Trundle bed with super single mattress",
    "description": "Dunlopillow Moments trundle bed + Super Single top (with 6\" spring coil Dunlopillow Harmony mattress) + Single bottom (with rollers & lift up legs).\nWhen the single bottom is lifted up, it is level with the super single top, and becomes queen size.\nGot it from someone else, but have not used it due to space constraint.\nBoth frames + mattress have been thoroughly wiped down + vacuumed.\nWill dismantle and shrink wrap for delivery.",
    "location": "Geylang, Eunos",
    "validTill": "23 Oct 2023",
    "ageInYears": 2,
    "dimensions": null,
    "deliveryCostsCoveredByDonor": true
  },
  {
    "id": "127071",
    "name": "black colour study table",
    "description": "black colour study table",
    "location": "Serangoon Garden, Hougang, Ponggol",
    "validTill": "16 Nov 2023",
    "ageInYears": 2,
    "dimensions": "100cm X 60cm X 74cm",
    "deliveryCostsCoveredByDonor": true
  },
  {
    "id": "127070",
    "name": "black colour study table",
    "description": "black colour study table",
    "location": "Serangoon Garden, Hougang, Ponggol",
    "validTill": "16 Nov 2023",
    "ageInYears": 2,
    "dimensions": "100cm X 60cm X 74 cm",
    "deliveryCostsCoveredByDonor": true
  },
  {
    "id": "127069",
    "name": "Ikea Study Table",
    "description": "Colour: dark brown. Comes with 1 drawer, which is rather shallow so can only store statiobery. Size: 73cm (L) x 50cm (W) x 75cm (H)",
    "location": null,
    "validTill": "29 Oct 2023",
    "ageInYears": 2,
    "dimensions": null,
    "deliveryCostsCoveredByDonor": true
  },
  {
    "id": "127068",
    "name": "study table",
    "description": "white colour study / computer table",
    "location": "Serangoon Garden, Hougang, Ponggol",
    "validTill": "16 Nov 2023",
    "ageInYears": 2,
    "dimensions": "100cm X 60cm X 74cm",
    "deliveryCostsCoveredByDonor": true
  },
  {
    "id": "127067",
    "name": "multipurpose shelves",
    "description": "multipurpose shelves",
    "location": "Serangoon Garden, Hougang, Ponggol",
    "validTill": "16 Nov 2023",
    "ageInYears": 2,
    "dimensions": "60cm X 42cm X 130cm",
    "deliveryCostsCoveredByDonor": true
  },
  {
    "id": "127066",
    "name": "bookshelves with adjustable shelving",
    "description": "bookshelves with adjustable shelves",
    "location": "Serangoon Garden, Hougang, Ponggol",
    "validTill": "16 Nov 2023",
    "ageInYears": 2,
    "dimensions": "120cm X 42cm X 130cm",
    "deliveryCostsCoveredByDonor": true
  },
  {
    "id": "127065",
    "name": "queen size bed with bedframe & mattress",
    "description": "queen size bed with bedframe & mattress.  collection on 28 Nov 2023",
    "location": "Serangoon Garden, Hougang, Ponggol",
    "validTill": "16 Nov 2023",
    "ageInYears": 2,
    "dimensions": null,
    "deliveryCostsCoveredByDonor": true
  },
  {
    "id": "127064",
    "name": "queen size bed with bed frame & mattress",
    "description": "queen size bed with bedframe & mattress.  collection on 28 Nov.",
    "location": "Serangoon Garden, Hougang, Ponggol",
    "validTill": "16 Nov 2023",
    "ageInYears": 2,
    "dimensions": null,
    "deliveryCostsCoveredByDonor": true
  },
  {
    "id": "127063",
    "name": "Commode",
    "description": "Please WhatsApp if you are keen to have the item delivered \nThanks",
    "location": "Queenstown, Tiong Bahru",
    "validTill": "01 Nov 2023",
    "ageInYears": 2,
    "dimensions": null,
    "deliveryCostsCoveredByDonor": true
  },
  {
    "id": "127062",
    "name": "Child play slide",
    "description": "Child play slide from Little Tikes. Self-collection please if possible.",
    "location": "Yishun, Sembawang",
    "validTill": "29 Oct 2023",
    "ageInYears": 3,
    "dimensions": "110x90x100cm",
    "deliveryCostsCoveredByDonor": true
  },
  {
    "id": "127053",
    "name": "Study Table",
    "description": "Study table in very good condition.",
    "location": "Tampines, Pasir Ris",
    "validTill": "20 Oct 2023",
    "ageInYears": 4,
    "dimensions": "121cm x 60cm x 197cm",
    "deliveryCostsCoveredByDonor": true
  },
  {
    "id": "127038",
    "name": "Study table and chair",
    "description": "Tall study table and single chair.. can be used as a multipurpose side table as well",
    "location": "Bedok, Upper East Coast, Eastwood, Kew Drive",
    "validTill": "05 Nov 2023",
    "ageInYears": 2,
    "dimensions": null,
    "deliveryCostsCoveredByDonor": true
  },
  {
    "id": "127037",
    "name": "Wooden storage box",
    "description": "Versatile wooden storage box that can be placed outdoor or indoor. Good for storing equipment, tools, swimming equipment, toys or gardening supplies.",
    "location": "Balestier, Toa Payoh, Serangoon",
    "validTill": "28 Oct 2023",
    "ageInYears": 4,
    "dimensions": "61cm (length) x 51cm (breadth) x 57cm (height)",
    "deliveryCostsCoveredByDonor": true
  },
  {
    "id": "127032",
    "name": "T-shirts",
    "description": "Size L",
    "location": "Yishun, Sembawang",
    "validTill": "15 Nov 2023",
    "ageInYears": 2,
    "dimensions": null,
    "deliveryCostsCoveredByDonor": true
  },
  {
    "id": "127014",
    "name": "Lactulose 200 ml , 12 bottles",
    "description": "200ml Duphalac (667g/l lactulose) for clearing of bowels",
    "location": null,
    "validTill": "15 Nov 2023",
    "ageInYears": 1,
    "dimensions": null,
    "deliveryCostsCoveredByDonor": true
  },
  {
    "id": "127012",
    "name": "Kids bed",
    "description": "2 bed available, pink and white\n\nUsed kids bed, can sleep up to primary 3\nCome along with all the mattress cover.",
    "location": "Yishun, Sembawang",
    "validTill": "15 Nov 2023",
    "ageInYears": 2,
    "dimensions": null,
    "deliveryCostsCoveredByDonor": true
  },
  {
    "id": "126996",
    "name": "Stool",
    "description": "2 pcs of old stools. Usable condition",
    "location": "Tampines, Pasir Ris",
    "validTill": "14 Nov 2023",
    "ageInYears": 4,
    "dimensions": null,
    "deliveryCostsCoveredByDonor": true
  },
  {
    "id": "126990",
    "name": "2 white chairs with adjustable height",
    "description": "2 white chairs with adjustable heights.\nLowest height - 57 cam\nTallest height - 77 cm",
    "location": "Serangoon Garden, Hougang, Ponggol",
    "validTill": "14 Nov 2023",
    "ageInYears": 2,
    "dimensions": "adjustable heights",
    "deliveryCostsCoveredByDonor": true
  },
  {
    "id": "126988",
    "name": "wooden dining table",
    "description": "wooden foldable (140cm) / extendable (260cm) dining table with 4 single wooden foldable chairs and a 2 seater bench. can be used indoor or outdoor. Originally bought from Ikea with photo attached.",
    "location": "Serangoon Garden, Hougang, Ponggol",
    "validTill": "14 Nov 2023",
    "ageInYears": 2,
    "dimensions": "folded length 140cm.  extended length 260cm.",
    "deliveryCostsCoveredByDonor": true
  },
  {
    "id": "126987",
    "name": "2seater",
    "description": "2 pcs",
    "location": "Tampines, Pasir Ris",
    "validTill": "14 Nov 2023",
    "ageInYears": 4,
    "dimensions": null,
    "deliveryCostsCoveredByDonor": true
  },
  {
    "id": "126979",
    "name": "Aircast Airselect Short Boot",
    "description": "The Aircast AirSelect Short Walker is designed to provide support and immobilization to the ankle. Suitable for treatment of stable fractures of the foot, lateral ankle sprains or ligamentous injuries such as Plantar Fasciitis, AS RECOMMENDED BY YOUR OWN DOCTOR",
    "location": "Ardmore, Bukit Timah, Holland Road, Tanglin",
    "validTill": "14 Nov 2023",
    "ageInYears": 1,
    "dimensions": "Short",
    "deliveryCostsCoveredByDonor": true
  },
  {
    "id": "126978",
    "name": "Framed jigsaw puzzles (3 pcs)",
    "description": "Framed jigsaw puzzles for wall decoration (each 1000 pcs, 50x75 cm)",
    "location": "Yishun, Sembawang",
    "validTill": "14 Nov 2023",
    "ageInYears": 3,
    "dimensions": "50x75 cm",
    "deliveryCostsCoveredByDonor": true
  },
  {
    "id": "126977",
    "name": "Office chair (professional dark blue)",
    "description": "Professional looking and comfortable dark blue office chair.",
    "location": "Balestier, Toa Payoh, Serangoon",
    "validTill": "28 Oct 2023",
    "ageInYears": 4,
    "dimensions": "Height 1.31m",
    "deliveryCostsCoveredByDonor": true
  },
  {
    "id": "126976",
    "name": "Office chair",
    "description": "Sturdy office chair with comfortable cushion and backrest. Right handle slightly worn.",
    "location": "Balestier, Toa Payoh, Serangoon",
    "validTill": "28 Oct 2023",
    "ageInYears": 4,
    "dimensions": "Height around 1.4m (tall back rest)",
    "deliveryCostsCoveredByDonor": true
  },
  {
    "id": "126975",
    "name": "Coffee table",
    "description": "Wooden side table with drawers and both ends.",
    "location": "Balestier, Toa Payoh, Serangoon",
    "validTill": "28 Oct 2023",
    "ageInYears": 4,
    "dimensions": "1m x 0.5m x 0.7m",
    "deliveryCostsCoveredByDonor": true
  },
  {
    "id": "126974",
    "name": "Bedside table x 2",
    "description": "Wooden side table with black top surface, well maintained. Has a drawer to place personal belongings. Can last 10 years.",
    "location": "Balestier, Toa Payoh, Serangoon",
    "validTill": "28 Oct 2023",
    "ageInYears": 4,
    "dimensions": "52cm length x 47cm breadth x 45cm height",
    "deliveryCostsCoveredByDonor": true
  },
  {
    "id": "126972",
    "name": "Study desk",
    "description": "Almost new condition study desk. Can place multiple computer screens or file racks as necessary. Will last 20 years if well maintained.",
    "location": "Balestier, Toa Payoh, Serangoon",
    "validTill": "28 Oct 2023",
    "ageInYears": 4,
    "dimensions": "1.6m x 62cm x 45cm",
    "deliveryCostsCoveredByDonor": true
  },
  {
    "id": "126953",
    "name": "Marble Dining Table w Lazy Susan + 3 chairs",
    "description": "Round marble table with lazy susan & 3 dining chairs",
    "location": "Bedok, Upper East Coast, Eastwood, Kew Drive",
    "validTill": "31 Oct 2023",
    "ageInYears": 4,
    "dimensions": "Diameter: 120cm Height: 66cm",
    "deliveryCostsCoveredByDonor": true
  },
  {
    "id": "126934",
    "name": "Smart casual T-shirts (short sleeves)",
    "description": "Shirts are close to new. Either wear once or never wear before (just washed)\n\nI have about 5-6 pieces up for grabs.",
    "location": "Kranji, Woodgrove",
    "validTill": "12 Nov 2023",
    "ageInYears": 1,
    "dimensions": null,
    "deliveryCostsCoveredByDonor": true
  },
  {
    "id": "126923",
    "name": "Walking Frame",
    "description": "Bought this item about a month ago, very new.",
    "location": null,
    "validTill": "31 Oct 2023",
    "ageInYears": 1,
    "dimensions": null,
    "deliveryCostsCoveredByDonor": true
  },
  {
    "id": "126918",
    "name": "Kenwood Oven Toadter",
    "description": "This oven toaster bought 4 years ago, it is still working well.",
    "location": null,
    "validTill": "31 Oct 2023",
    "ageInYears": 4,
    "dimensions": null,
    "deliveryCostsCoveredByDonor": true
  },
  {
    "id": "126848",
    "name": "Om Dining Table",
    "description": "Om brand. Solid glass table",
    "location": "Ardmore, Bukit Timah, Holland Road, Tanglin",
    "validTill": "03 Nov 2023",
    "ageInYears": 4,
    "dimensions": "160 cm x 80cm",
    "deliveryCostsCoveredByDonor": true
  },
  {
    "id": "126845",
    "name": "Hospital Bed",
    "description": "Hospital bed with 3 function super low electric.",
    "location": "Telok Blangah, Harbourfront",
    "validTill": "10 Nov 2023",
    "ageInYears": 4,
    "dimensions": "216cm by 102cm (Ht adjustable)",
    "deliveryCostsCoveredByDonor": true
  },
  {
    "id": "126826",
    "name": "8 black stackable chairs",
    "description": "6 black stackable chairs with back rest",
    "location": "Serangoon Garden, Hougang, Ponggol",
    "validTill": "09 Nov 2023",
    "ageInYears": 4,
    "dimensions": null,
    "deliveryCostsCoveredByDonor": true
  },
  {
    "id": "126758",
    "name": "Assortment of Hangers",
    "description": "Assortment of hangers to pass it on.",
    "location": "Orchard, Cairnhill, River Valley",
    "validTill": "01 Nov 2023",
    "ageInYears": 4,
    "dimensions": null,
    "deliveryCostsCoveredByDonor": true
  },
  {
    "id": "126739",
    "name": "Baby cot",
    "description": "Cot used for 3 years by 1 kid. Still in good condition (minor scratches where cot mobile was attached) and preloved mattress and covers can be provided if necessary too). Cot has wheels and drop side on one side for easier access to carry baby.",
    "location": null,
    "validTill": "20 Oct 2023",
    "ageInYears": 1,
    "dimensions": "120cm x 60cm x 98 cm",
    "deliveryCostsCoveredByDonor": true
  },
  {
    "id": "126727",
    "name": "Yamaha Upright Piano with Storage Bench",
    "description": "Pre-Loved Childhood Piano to bless to any charity organisations who might love to have this at their premises, or any individual beneficiary who would love to have a piano for leisure playing/learning. Item is about 40 years old. Comes with ( Storage bench for books and Piano Cover Fabric. Downsizing and moving house thus needing to let go of this. Happy to arrange for transport and also Piano tuning upon delivery.",
    "location": "Orchard, Cairnhill, River Valley",
    "validTill": "01 Nov 2023",
    "ageInYears": 4,
    "dimensions": "150cm x 70cm x 130cm",
    "deliveryCostsCoveredByDonor": true
  },
  {
    "id": "126785",
    "name": "baby cot",
    "description": "baby cot",
    "location": "Hillview, Dairy Farm, Bukit Panjang, Choa Chu Kang",
    "validTill": "07 Nov 2023",
    "ageInYears": 2,
    "dimensions": "1.5 x 0.5 x 1",
    "deliveryCostsCoveredByDonor": true
  },
  {
    "id": "126711",
    "name": "Hospital bed",
    "description": "Hospital to be given away.",
    "location": "Hillview, Dairy Farm, Bukit Panjang, Choa Chu Kang",
    "validTill": "07 Nov 2023",
    "ageInYears": 3,
    "dimensions": null,
    "deliveryCostsCoveredByDonor": true
  },
  {
    "id": "126704",
    "name": "Office chair",
    "description": "Self collect only",
    "location": "Little India",
    "validTill": "31 Oct 2023",
    "ageInYears": 2,
    "dimensions": "Depth:&nbsp;68 cm  Max. height:&nbsp;140 cm  Max. seat height:&nbsp;56 cm  Min. seat height:&nbsp;45 cm  Seat depth:&nbsp;46 cm  Seat width:&nbsp;52 cm   Width:&nbsp;68 cm",
    "deliveryCostsCoveredByDonor": true
  },
  {
    "id": "126646",
    "name": "Cushion cover (New)",
    "description": "New.",
    "location": null,
    "validTill": "04 Nov 2023",
    "ageInYears": 1,
    "dimensions": null,
    "deliveryCostsCoveredByDonor": true
  },
  {
    "id": "126588",
    "name": "VACOped achillies boot",
    "description": "Large size. Used for less than 3 weeks. Excellent condition.",
    "location": "Serangoon Garden, Hougang, Ponggol",
    "validTill": "02 Nov 2023",
    "ageInYears": 1,
    "dimensions": null,
    "deliveryCostsCoveredByDonor": true
  },
  {
    "id": "126532",
    "name": "LED candle, mobile phone fan and air tag case",
    "description": "LED candle - 4 nos.\nMobile phone fan - 1 no.\nAir tag case - 1 no.",
    "location": null,
    "validTill": "31 Oct 2023",
    "ageInYears": 1,
    "dimensions": null,
    "deliveryCostsCoveredByDonor": true
  },
  {
    "id": "126501",
    "name": "Food container",
    "description": "Small heat retainer container",
    "location": "Yishun, Sembawang",
    "validTill": "31 Oct 2023",
    "ageInYears": 3,
    "dimensions": null,
    "deliveryCostsCoveredByDonor": true
  },
  {
    "id": "126493",
    "name": "Floor tiles",
    "description": "Floor tiles.",
    "location": "Balestier, Toa Payoh, Serangoon",
    "validTill": "31 Oct 2023",
    "ageInYears": 1,
    "dimensions": null,
    "deliveryCostsCoveredByDonor": true
  },
  {
    "id": "126491",
    "name": "Shower chair",
    "description": "Chair for showering",
    "location": null,
    "validTill": "30 Oct 2023",
    "ageInYears": 4,
    "dimensions": null,
    "deliveryCostsCoveredByDonor": true
  },
  {
    "id": "126571",
    "name": "Walking stick",
    "description": "Walking stick, well used.",
    "location": "Queenstown, Tiong Bahru",
    "validTill": "30 Oct 2023",
    "ageInYears": 4,
    "dimensions": null,
    "deliveryCostsCoveredByDonor": true
  },
  {
    "id": "126572",
    "name": "Walking stick",
    "description": "Walking stick, well used.",
    "location": "Queenstown, Tiong Bahru",
    "validTill": "30 Oct 2023",
    "ageInYears": 4,
    "dimensions": null,
    "deliveryCostsCoveredByDonor": true
  },
  {
    "id": "126489",
    "name": "Commode",
    "description": "Commode",
    "location": "Queenstown, Tiong Bahru",
    "validTill": "30 Oct 2023",
    "ageInYears": 4,
    "dimensions": null,
    "deliveryCostsCoveredByDonor": true
  },
  {
    "id": "126488",
    "name": "Walking frame",
    "description": "Walking frame, well used",
    "location": null,
    "validTill": "30 Oct 2023",
    "ageInYears": 4,
    "dimensions": null,
    "deliveryCostsCoveredByDonor": true
  },
  {
    "id": "126478",
    "name": "Kids clothes and toys",
    "description": "Various pre-loved baby/toddler girl clothes and toys suitable for ages 0 - 3",
    "location": "Tampines, Pasir Ris",
    "validTill": "29 Oct 2023",
    "ageInYears": 3,
    "dimensions": null,
    "deliveryCostsCoveredByDonor": true
  },
  {
    "id": "126476",
    "name": "Study Desk",
    "description": "Study desk\nBought from Ikea\nSlight stain on surface",
    "location": "Hillview, Dairy Farm, Bukit Panjang, Choa Chu Kang",
    "validTill": "29 Oct 2023",
    "ageInYears": 3,
    "dimensions": "1300(L)x600(D)x740(H) mm",
    "deliveryCostsCoveredByDonor": true
  },
  {
    "id": "126474",
    "name": "Exercise Mat",
    "description": "Giving away exercise mats which are too thin for my usage.",
    "location": "Jurong",
    "validTill": "29 Oct 2023",
    "ageInYears": 1,
    "dimensions": "173cm x 61cm x 6mm",
    "deliveryCostsCoveredByDonor": true
  },
  {
    "id": "126460",
    "name": "High Chair",
    "description": "High chair not for picky user",
    "location": "Bishan, Ang Mo Kio",
    "validTill": "28 Oct 2023",
    "ageInYears": 4,
    "dimensions": null,
    "deliveryCostsCoveredByDonor": true
  },
  {
    "id": "126409",
    "name": "Walker",
    "description": "Foldable walking frame in good condition",
    "location": "Anson, Tanjong Pagar",
    "validTill": "27 Oct 2023",
    "ageInYears": 4,
    "dimensions": null,
    "deliveryCostsCoveredByDonor": true
  },
  {
    "id": "126740",
    "name": "cap for digital thermometer",
    "description": "disposable medical cap for thermometer for hospital use or elderly care, quantity 3800 pcs. New item, never open.           \n\nNote: self collection at 131 rifle range road. Temasek Club. Thanks",
    "location": "Ardmore, Bukit Timah, Holland Road, Tanglin",
    "validTill": "26 Oct 2023",
    "ageInYears": 1,
    "dimensions": "100cm *100am",
    "deliveryCostsCoveredByDonor": true
  },
  {
    "id": "126290",
    "name": "Cantonese Opera VCDs (Many)",
    "description": "Looking for community service to take this for elderly who enjoys cantonese opera shows in the 60 to 80s. Many of these opera are hard to comedy and used to be enjoyed by the cantonese seniors.\n\nIf not donated to cantonese group which can still copy over into disc or watch over with a disc player, hope they are usefully enjoyed by a matched donee.",
    "location": "Serangoon Garden, Hougang, Ponggol",
    "validTill": "23 Oct 2023",
    "ageInYears": 4,
    "dimensions": null,
    "deliveryCostsCoveredByDonor": true
  },
  {
    "id": "126268",
    "name": "IKEA Antilop Highchair with tray",
    "description": "Lightly used. Like new. Pink chair, white tray.",
    "location": "Jalan Tenaga",
    "validTill": "22 Oct 2023",
    "ageInYears": 1,
    "dimensions": null,
    "deliveryCostsCoveredByDonor": true
  },
  {
    "id": "126101",
    "name": "Porcelain Bowls",
    "description": "6 porcelain bowls",
    "location": null,
    "validTill": "20 Oct 2023",
    "ageInYears": 4,
    "dimensions": null,
    "deliveryCostsCoveredByDonor": true
  }
]