[
  {
    "id": "128363",
    "name": "TV 42”",
    "description": "Used but good working condition 42” TV",
    "location": "Hillview, Dairy Farm, Bukit Panjang, Choa Chu Kang",
    "validTill": "10 Dec 2023",
    "ageInYears": 4,
    "dimensions": "42”",
    "deliveryCostsCoveredByDonor": true
  },
  {
    "id": "128362",
    "name": "Fridge samsung RT53eamt",
    "description": "In good working condition, old but has always worked fine. only external door looks patchy due to stickers previously.\nGiving away as buying new fridge. Collection will need to be timed with new fridge.",
    "location": "Bishan, Ang Mo Kio",
    "validTill": "30 Nov 2023",
    "ageInYears": 4,
    "dimensions": "W 720cm D 700 height about 1800",
    "deliveryCostsCoveredByDonor": true
  },
  {
    "id": "128361",
    "name": "Super single bed",
    "description": "Lightly used and spotless super single bed",
    "location": "Macpherson, Braddell",
    "validTill": "26 Dec 2023",
    "ageInYears": 1,
    "dimensions": null,
    "deliveryCostsCoveredByDonor": true
  },
  {
    "id": "128357",
    "name": "Tricycle for child 6 months to 5 years old",
    "description": "Item is a tricycle for child 6 months to 5 years old\n\nThis item is new in box\nRequires assembly\nPlease collect from address",
    "location": null,
    "validTill": "25 Dec 2023",
    "ageInYears": 1,
    "dimensions": null,
    "deliveryCostsCoveredByDonor": true
  },
  {
    "id": "128356",
    "name": "Clean Super single hard matress",
    "description": "Clean spring mattress 4 Stars Brand hard",
    "location": "Queenstown, Tiong Bahru",
    "validTill": "25 Dec 2023",
    "ageInYears": 4,
    "dimensions": "L 190cm x W 90cm x H 23cm",
    "deliveryCostsCoveredByDonor": true
  },
  {
    "id": "128355",
    "name": "Duphalac (lactulose)",
    "description": "9 btls (new) 200 ml each\nSee photo",
    "location": "Upper Thomson, Springleaf",
    "validTill": "25 Dec 2023",
    "ageInYears": 1,
    "dimensions": null,
    "deliveryCostsCoveredByDonor": true
  },
  {
    "id": "128354",
    "name": "Tena adult pull up diaper (M)",
    "description": "Nil",
    "location": "Upper Thomson, Springleaf",
    "validTill": "25 Dec 2023",
    "ageInYears": 1,
    "dimensions": null,
    "deliveryCostsCoveredByDonor": true
  },
  {
    "id": "128353",
    "name": "Electric lamp",
    "description": "LED table lamp",
    "location": "Balestier, Toa Payoh, Serangoon",
    "validTill": "10 Dec 2023",
    "ageInYears": 2,
    "dimensions": null,
    "deliveryCostsCoveredByDonor": true
  },
  {
    "id": "128352",
    "name": "Electric kettle",
    "description": "Morries electric kettle, less than 1 year old",
    "location": "Balestier, Toa Payoh, Serangoon",
    "validTill": "10 Dec 2023",
    "ageInYears": 1,
    "dimensions": null,
    "deliveryCostsCoveredByDonor": true
  },
  {
    "id": "128351",
    "name": "TV",
    "description": "Comes with digital set top box",
    "location": "Balestier, Toa Payoh, Serangoon",
    "validTill": "10 Dec 2023",
    "ageInYears": 4,
    "dimensions": null,
    "deliveryCostsCoveredByDonor": true
  },
  {
    "id": "128347",
    "name": "Ikea SMÅSTAD / PLATSA Wardrobe Cabinet Bookcase 60x57x123 cm",
    "description": "- Almost new! Lightly used only.\n- Free 30 hangers!",
    "location": "Telok Blangah, Harbourfront",
    "validTill": "08 Dec 2023",
    "ageInYears": 1,
    "dimensions": "60x57x123 cm",
    "deliveryCostsCoveredByDonor": true
  },
  {
    "id": "128315",
    "name": "Arm chair",
    "description": "A good armchair for the elderly.",
    "location": "Tampines, Pasir Ris",
    "validTill": "21 Dec 2023",
    "ageInYears": 2,
    "dimensions": "L 70 cm, W 77 cm, H 100cm",
    "deliveryCostsCoveredByDonor": true
  },
  {
    "id": "128313",
    "name": "Cabinet",
    "description": "3 tiered glass shelf , drawer below",
    "location": "Bedok, Upper East Coast, Eastwood, Kew Drive",
    "validTill": "24 Dec 2023",
    "ageInYears": 3,
    "dimensions": "Depth 40cm , height 120 cm , width 69 cm",
    "deliveryCostsCoveredByDonor": true
  },
  {
    "id": "128295",
    "name": "philip avent sterilizer and dryer",
    "description": "Philip Avent Sterilizer and Dryer. Used for less than 1 year and is in good condition.",
    "location": "Balestier, Toa Payoh, Serangoon",
    "validTill": "08 Dec 2023",
    "ageInYears": 1,
    "dimensions": "19cm x 30cm x 37cm",
    "deliveryCostsCoveredByDonor": true
  },
  {
    "id": "128288",
    "name": "ROCKING CHAIR",
    "description": "Wooden rocking chair\nGood pcondition",
    "location": "Serangoon Garden, Hougang, Ponggol",
    "validTill": "30 Nov 2023",
    "ageInYears": 4,
    "dimensions": null,
    "deliveryCostsCoveredByDonor": true
  },
  {
    "id": "128287",
    "name": "LEATHER SOFA",
    "description": "2 Seaters leather sofa",
    "location": "Serangoon Garden, Hougang, Ponggol",
    "validTill": "30 Nov 2023",
    "ageInYears": 4,
    "dimensions": null,
    "deliveryCostsCoveredByDonor": true
  },
  {
    "id": "128284",
    "name": "2 x QUEENS SIZE BEDS. 1 x SINGLE BED",
    "description": "2 x QUEENS SIZE BEDS \n1 x SINGLE BED",
    "location": "Serangoon Garden, Hougang, Ponggol",
    "validTill": "30 Nov 2023",
    "ageInYears": 4,
    "dimensions": null,
    "deliveryCostsCoveredByDonor": true
  },
  {
    "id": "128282",
    "name": "Creative speakers",
    "description": "A pair of creative speakers (USB)",
    "location": "Upper Thomson, Springleaf",
    "validTill": "23 Dec 2023",
    "ageInYears": 4,
    "dimensions": null,
    "deliveryCostsCoveredByDonor": true
  },
  {
    "id": "128281",
    "name": "Logitec speakers with power input",
    "description": "A pair of logitec speaker with power input",
    "location": "Upper Thomson, Springleaf",
    "validTill": "23 Dec 2023",
    "ageInYears": 4,
    "dimensions": null,
    "deliveryCostsCoveredByDonor": true
  },
  {
    "id": "128317",
    "name": "3tiers / 5 tiers steel open shelve racks",
    "description": "Dear all VWOs, \nI have a few quantity so please do not click on reserved as the posting will disappear and i have to repost again :( Kindly contact me first if you are interested and I can reserve for you on first come first serve basis \n\n1) 3 tiers (184cm x 92cm x 47cm)\n2) 5 tiers (212cm x 122cm x 47xcm)\n3) 5 tiers (212cm x 92cm x 47xcm)",
    "location": "Upper Thomson, Springleaf",
    "validTill": "22 Dec 2023",
    "ageInYears": 4,
    "dimensions": "Various dimensions.",
    "deliveryCostsCoveredByDonor": true
  },
  {
    "id": "128261",
    "name": "Baby cot",
    "description": "Solid wooden cot. Dimensions as follows.\nLength and 141cm\nWidth 80cm\nHeight 113cm\n\nCan deliver anywhere in Singapore",
    "location": null,
    "validTill": "23 Dec 2023",
    "ageInYears": 3,
    "dimensions": null,
    "deliveryCostsCoveredByDonor": true
  },
  {
    "id": "128259",
    "name": "Foldaway Bumper Playmat",
    "description": "-Measurements & colours are as in the image\n-It is well used, so some stains are expected, but still in good and usable condition\n-Can be used as a baby floot cot too",
    "location": "Pasir Panjang, Hong Leong Garden, Clementi New Town",
    "validTill": "23 Dec 2023",
    "ageInYears": 4,
    "dimensions": "1400x1000x500",
    "deliveryCostsCoveredByDonor": true
  },
  {
    "id": "128250",
    "name": "Foldable table, small",
    "description": "Foldable table, rarely used except during parties",
    "location": "Balestier, Toa Payoh, Serangoon",
    "validTill": "23 Dec 2023",
    "ageInYears": 1,
    "dimensions": "40cm x 69cm x 64cm (height)",
    "deliveryCostsCoveredByDonor": true
  },
  {
    "id": "128249",
    "name": "Piano 120 CM upright",
    "description": "This is NOT a piece of junk like most giveaway pianos. Just tuned Nov 23, 30+ years but can last another 20 years. tuned twice a year. Made in Japan. Beautiful respectable condition. Center muting pedal not working but no need repair if not using for sound muting. Nice for senior activity home etc.",
    "location": "Bukit Panjang ",
    "validTill": "23 Dec 2023",
    "ageInYears": 4,
    "dimensions": "120 cm standard upright",
    "deliveryCostsCoveredByDonor": true
  },
  {
    "id": "128247",
    "name": "dressing table",
    "description": "The dressing table is still in a very good condition.\nCollection can only be done from 4 - 6 Dec only.",
    "location": "Telok Blangah, Harbourfront",
    "validTill": "06 Dec 2023",
    "ageInYears": 3,
    "dimensions": null,
    "deliveryCostsCoveredByDonor": true
  },
  {
    "id": "128242",
    "name": "King size Bed frame with 4 drawers",
    "description": "Well kept King size bed frame",
    "location": "Tampines, Pasir Ris",
    "validTill": "01 Dec 2023",
    "ageInYears": 4,
    "dimensions": null,
    "deliveryCostsCoveredByDonor": true
  },
  {
    "id": "128240",
    "name": "Metal frame",
    "description": "The walking fame is used by my mum which height about 160 c.",
    "location": "Queenstown, Tiong Bahru",
    "validTill": "23 Dec 2023",
    "ageInYears": 3,
    "dimensions": null,
    "deliveryCostsCoveredByDonor": true
  },
  {
    "id": "128171",
    "name": "Dining Chairs - 2 sets of 2",
    "description": "Two sets of dining chairs available. They are identical except that 2 of them have stoppers and are about 1cm taller than the other 2. All 4 can be used as a set.",
    "location": "Tampines, Pasir Ris",
    "validTill": "02 Dec 2023",
    "ageInYears": 2,
    "dimensions": "46cmx46cmx80cm",
    "deliveryCostsCoveredByDonor": true
  },
  {
    "id": "128159",
    "name": "Hospital bed",
    "description": "This 3 Crank Electrical Luxury Hospital Bed has split side panels that follow the back raising reclining feature. Increased safety and stability when getting on and off the bed while holding on to the side rails.\nWill cover partial or full for the transport fee for the needy.",
    "location": null,
    "validTill": "21 Dec 2023",
    "ageInYears": 1,
    "dimensions": null,
    "deliveryCostsCoveredByDonor": true
  },
  {
    "id": "128120",
    "name": "Walking frame",
    "description": "Hardly L- used walking frame . Please email as I \nOut of town in a different timezone.",
    "location": null,
    "validTill": "01 Dec 2023",
    "ageInYears": 1,
    "dimensions": null,
    "deliveryCostsCoveredByDonor": true
  },
  {
    "id": "128118",
    "name": "Commode",
    "description": "Barely used commode. Note that cover is missing . \nPls email as I am out of town and in different timezone .",
    "location": "Yishun, Sembawang",
    "validTill": "01 Dec 2023",
    "ageInYears": 1,
    "dimensions": null,
    "deliveryCostsCoveredByDonor": true
  },
  {
    "id": "128115",
    "name": "Tricycle",
    "description": "Crack in the basket at the back but taped up.",
    "location": "Yishun, Sembawang",
    "validTill": "20 Dec 2023",
    "ageInYears": 3,
    "dimensions": null,
    "deliveryCostsCoveredByDonor": true
  },
  {
    "id": "128110",
    "name": "Home bakes",
    "description": "We are group of home bakers looking to bake and bless with charity for school holiday/Xmas seasons. Our FB is SG Blessing Bakers. we do have frequent bakes for blessing Q too. Bake items/Quantity/Collection point to be discussed.",
    "location": "Bishan, Ang Mo Kio",
    "validTill": "20 Dec 2023",
    "ageInYears": 2,
    "dimensions": null,
    "deliveryCostsCoveredByDonor": true
  },
  {
    "id": "128100",
    "name": "Baby bathtub",
    "description": "Pre-loved bathtub in good condition",
    "location": "Serangoon Garden, Hougang, Ponggol",
    "validTill": "20 Dec 2023",
    "ageInYears": 1,
    "dimensions": null,
    "deliveryCostsCoveredByDonor": true
  },
  {
    "id": "128099",
    "name": "Baby bouncer/rocker",
    "description": "pre-loved baby bouncer/rocker. item can either be fixed or can also remove the legs to make it rock.",
    "location": "Serangoon Garden, Hougang, Ponggol",
    "validTill": "20 Dec 2023",
    "ageInYears": 1,
    "dimensions": null,
    "deliveryCostsCoveredByDonor": true
  },
  {
    "id": "128081",
    "name": "Baby Foldable Bathtub",
    "description": "Foldable baby bathtub in blue colour. Can be folded for easy storage. Still in good condition. Only used for less than 1 year.",
    "location": "Balestier, Toa Payoh, Serangoon",
    "validTill": "08 Dec 2023",
    "ageInYears": 1,
    "dimensions": "82cm x 52cm x 22cm",
    "deliveryCostsCoveredByDonor": true
  },
  {
    "id": "128074",
    "name": "Child's bed with mattress",
    "description": "Child/ toddler bed with mattress. Mattress  is 80% new and mostly used in air-conditioned room. I am happy to include a couple of bedsheets that are specific to the size of the mattress as well. The bed has already been dismantled, the recipient will need to put it together on their own. Details of the bed, including assembly directions: https://www.ikea.com/sg/en/p/kritter-bed-frame-with-slatted-bed-base-white-s39240344/",
    "location": "Bishan, Ang Mo Kio",
    "validTill": "19 Dec 2023",
    "ageInYears": 3,
    "dimensions": "165 x 77 x 68cm",
    "deliveryCostsCoveredByDonor": true
  },
  {
    "id": "128073",
    "name": "Slow cooker",
    "description": "Seldom used slow cooker, Toyomi brand. Currently retailing at $93 in NTUC",
    "location": "Bishan, Ang Mo Kio",
    "validTill": "19 Dec 2023",
    "ageInYears": 2,
    "dimensions": "25cm by 25 cm by 24cm",
    "deliveryCostsCoveredByDonor": true
  },
  {
    "id": "128067",
    "name": "LITTLE TIKES CAR",
    "description": "LITTLE TIKES CAR for 2-3 years old",
    "location": "Serangoon Garden, Hougang, Ponggol",
    "validTill": "30 Nov 2023",
    "ageInYears": 4,
    "dimensions": null,
    "deliveryCostsCoveredByDonor": true
  },
  {
    "id": "128061",
    "name": "Commode",
    "description": "Used but in good condition. Aluminium frame. Lightweight.",
    "location": "Bishan, Ang Mo Kio",
    "validTill": "18 Dec 2023",
    "ageInYears": 2,
    "dimensions": null,
    "deliveryCostsCoveredByDonor": true
  },
  {
    "id": "128052",
    "name": "Sound blaster R3",
    "description": "i cant pay for delivery nor send to VWO. PLS PICK up FROM MY HOME.",
    "location": "Hillview, Dairy Farm, Bukit Panjang, Choa Chu Kang",
    "validTill": "12 Dec 2023",
    "ageInYears": 3,
    "dimensions": null,
    "deliveryCostsCoveredByDonor": true
  },
  {
    "id": "128013",
    "name": "Medela Harmony Manual Breast Pump",
    "description": "Used maybe 6 times.\n\nThe Medela Harmony Manual Breast Pump is designed for mums who mostly breastfeed and is great for travel or as a backup to your electric pump. Discreet, comfortable and gentle - For mums who intend to breastfeed all the time, small manual breast pumps may seem unnecessary, but it is always good to have something lightweight and compact on hand. Most mums will run into situations where they need to express milk for their own comfort. This pump is especially recommended for mums who travel: for use either as a backup for a double electric pump or on its own if you are not a frequent pumper. Light and discreet - Medela Harmony is a manual pump so it does not require electricity or batteries for operation and is almost silent. Its smooth operation will pleasantly surprise you when you start pumping. This is a very lightweight pump that does not take up much room in a handbag. Simple and elegant design - Medela Harmony's ergonomic design is intuitive and allows for very easy use. It is very simple to take apart and clean. The handle on the Medela Harmony manual breast pump has been designed to twist, so you can always get the best angle to pump the milk without having to move your arms into an uncomfortable position. The lever has a nice, soft rubber cover that makes pumping a little easier on your hands and helps the pump operate quietly. 2-Phase Expression technology - Medela Harmony is one of the few manual pumps in the world featuring 2-Phase Expression technology. The breast pump simulates the natural baby sucking behaviour at the mother's breast. The 2-Phase design simply means that to stimulate let down (when your milk begins to flow) you begin pumping with the shorter side of the pump's handle which creates a faster sucking cycle, similar to that of a hungry baby. Once the milk starts to flow, you switch to the longer side of the handle which creates a slower sucking cycle to express the majority of your milk. Product Features: Light and discreet: switch between this pump and a double electric pump or use this pump on its own if you do not pump frequently Elegantly designed and comfortable to use: assembly is intuitive and the pump has an ergonomic twist handle Features 2-Phase Expression technology The pump also comes with 1 x personal fit breast shield, 1 x breast milk bottle for collection and 1x bottle stand The included bottle collects expressed breastmilk ready for storing Operated by hand - requires no battery or mains supply Small, lightweight and easy to transport - perfect for on the go Almost silent during use Easy to use and clean Age recommendation: 0m+",
    "location": "Orchard, Cairnhill, River Valley",
    "validTill": "17 Dec 2023",
    "ageInYears": 1,
    "dimensions": null,
    "deliveryCostsCoveredByDonor": true
  },
  {
    "id": "127973",
    "name": "Writing pads and paper",
    "description": "Unused writing pads and writing paper accumulated over the years.",
    "location": "Ardmore, Bukit Timah, Holland Road, Tanglin",
    "validTill": "16 Dec 2023",
    "ageInYears": 4,
    "dimensions": null,
    "deliveryCostsCoveredByDonor": true
  },
  {
    "id": "128022",
    "name": "Baby cot",
    "description": "White baby cot used for a year only. In very good condition. Comes with mattress cover, mattress and bumpers.",
    "location": "Serangoon Garden, Hougang, Ponggol",
    "validTill": "30 Nov 2023",
    "ageInYears": 1,
    "dimensions": "124X66X84",
    "deliveryCostsCoveredByDonor": true
  },
  {
    "id": "127952",
    "name": "Black office/ study chair",
    "description": "Black chair with headrest and armrests, suitable for studying or work from home. Wheels are intact although one of the wheels does not move too smoothly. Otherwise, in good and clean condition.",
    "location": "Hillview, Dairy Farm, Bukit Panjang, Choa Chu Kang",
    "validTill": "15 Dec 2023",
    "ageInYears": 2,
    "dimensions": "65cm x 45cm x 110cm",
    "deliveryCostsCoveredByDonor": true
  },
  {
    "id": "127925",
    "name": "Nike Sneakers for Toddler",
    "description": "Nike sizing: 9C\nsuitable for kids between 1 year old onwards to 2 plus.",
    "location": "Yishun, Sembawang",
    "validTill": "15 Dec 2023",
    "ageInYears": 2,
    "dimensions": null,
    "deliveryCostsCoveredByDonor": true
  },
  {
    "id": "127901",
    "name": "Anmum Lacta",
    "description": "2 boxes of Formulated Milk Powder for Lactating Women",
    "location": "Hillview, Dairy Farm, Bukit Panjang, Choa Chu Kang",
    "validTill": "14 Dec 2023",
    "ageInYears": 1,
    "dimensions": null,
    "deliveryCostsCoveredByDonor": true
  },
  {
    "id": "127900",
    "name": "Dining Table and 6 Chairs (with covers)",
    "description": "A large pull extendable dining table and 6 chairs.  Old but still in good condition. Chair covers included.",
    "location": "Orchard, Cairnhill, River Valley",
    "validTill": "14 Dec 2023",
    "ageInYears": 4,
    "dimensions": null,
    "deliveryCostsCoveredByDonor": true
  },
  {
    "id": "127894",
    "name": "Brand new baby shoe",
    "description": "soft sole baby shoe. length 15cm",
    "location": "Serangoon Garden, Hougang, Ponggol",
    "validTill": "14 Dec 2023",
    "ageInYears": 1,
    "dimensions": "15cm",
    "deliveryCostsCoveredByDonor": true
  },
  {
    "id": "127893",
    "name": "Brand new toddlers shoe",
    "description": "brand new shoes for toddlers. length is 15.5cm",
    "location": "Serangoon Garden, Hougang, Ponggol",
    "validTill": "14 Dec 2023",
    "ageInYears": 1,
    "dimensions": "15.5cm length",
    "deliveryCostsCoveredByDonor": true
  },
  {
    "id": "127883",
    "name": "Babu playmat",
    "description": "Well used playmat that can be folded to smaller size, based on your needs. Some visible minor wear and tear but don't affect the purpose of the playmat.",
    "location": "Serangoon Garden, Hougang, Ponggol",
    "validTill": "14 Dec 2023",
    "ageInYears": 1,
    "dimensions": "180cm by 200cm",
    "deliveryCostsCoveredByDonor": true
  },
  {
    "id": "127868",
    "name": "Boy clothing",
    "description": "Boy clothing suitable for 6-8 years old depending on the child build.",
    "location": "Geylang, Eunos",
    "validTill": "14 Dec 2023",
    "ageInYears": 3,
    "dimensions": null,
    "deliveryCostsCoveredByDonor": true
  },
  {
    "id": "127862",
    "name": "school shoes white size 42",
    "description": "school white shoes\nhope this is near my neighbourhood to deliver",
    "location": null,
    "validTill": "30 Nov 2023",
    "ageInYears": 1,
    "dimensions": null,
    "deliveryCostsCoveredByDonor": true
  },
  {
    "id": "127861",
    "name": "Baby Playmat",
    "description": "Some wear and tear but still good condition.",
    "location": "Yishun, Sembawang",
    "validTill": "13 Dec 2023",
    "ageInYears": 2,
    "dimensions": "200cmx 150cm",
    "deliveryCostsCoveredByDonor": true
  },
  {
    "id": "127859",
    "name": "Pediasure Gold - Strawberry",
    "description": "Bought on the 12 Nov at Fairprice. Kept the receipt. Toddler is not used to the taste after trying it once.",
    "location": "Tampines, Pasir Ris",
    "validTill": "27 Nov 2023",
    "ageInYears": 2,
    "dimensions": null,
    "deliveryCostsCoveredByDonor": true
  },
  {
    "id": "127732",
    "name": "Antique furniture",
    "description": "Antique fur comes\nIn bed frame wardrobe and vanity table please\nCall\nMe\nFirst to discuss on transport cost before coming",
    "location": null,
    "validTill": "01 Dec 2023",
    "ageInYears": 4,
    "dimensions": null,
    "deliveryCostsCoveredByDonor": true
  },
  {
    "id": "127730",
    "name": "Soft toys (brand new)",
    "description": "Brand new soft toys. Unused and in very good condition.",
    "location": "Ardmore, Bukit Timah, Holland Road, Tanglin",
    "validTill": "07 Dec 2023",
    "ageInYears": 1,
    "dimensions": null,
    "deliveryCostsCoveredByDonor": true
  },
  {
    "id": "127668",
    "name": "Playpen",
    "description": "Hexagonal playpen. Good condition.\nEasy to dismantle, sturdy",
    "location": "Ardmore, Bukit Timah, Holland Road, Tanglin",
    "validTill": "06 Dec 2023",
    "ageInYears": 1,
    "dimensions": "124 x 124 x 66 cm",
    "deliveryCostsCoveredByDonor": true
  },
  {
    "id": "127622",
    "name": "Baby cot",
    "description": "Lightly used baby cot - used for only first 1.5 years and barely used after my child was older",
    "location": "Bedok, Upper East Coast, Eastwood, Kew Drive",
    "validTill": "03 Dec 2023",
    "ageInYears": 4,
    "dimensions": "132x73x102 cm",
    "deliveryCostsCoveredByDonor": true
  },
  {
    "id": "127584",
    "name": "Phlegm suction machine",
    "description": "A phlegm suction machine, plus 2 boxes of phlegm suction tubes",
    "location": "Serangoon Garden, Hougang, Ponggol",
    "validTill": "02 Dec 2023",
    "ageInYears": 3,
    "dimensions": null,
    "deliveryCostsCoveredByDonor": true
  },
  {
    "id": "127499",
    "name": "Birthday cake",
    "description": "Birthday cake for Blue chas family kiddo same birth date as 8 Nov. Please check out and Q at Facebook SG Blessing Bakers Group",
    "location": "Balestier, Toa Payoh, Serangoon",
    "validTill": "30 Nov 2023",
    "ageInYears": 1,
    "dimensions": null,
    "deliveryCostsCoveredByDonor": true
  },
  {
    "id": "127483",
    "name": "E-Chinese dictionary",
    "description": "E dictionary for secondary or junior college students",
    "location": null,
    "validTill": "29 Nov 2023",
    "ageInYears": 3,
    "dimensions": null,
    "deliveryCostsCoveredByDonor": true
  },
  {
    "id": "127462",
    "name": "Children umbrellas",
    "description": "Saniro umbrellas for children",
    "location": "Yishun, Sembawang",
    "validTill": "29 Nov 2023",
    "ageInYears": 4,
    "dimensions": null,
    "deliveryCostsCoveredByDonor": true
  }
]